manga_ocr/__init__.py
manga_ocr/__main__.py
manga_ocr/_version.py
manga_ocr/ocr.py
manga_ocr/run.py
manga_ocr/assets/example.jpg
manga_ocr-0.1.13.dist-info/LICENSE
manga_ocr-0.1.13.dist-info/METADATA
manga_ocr-0.1.13.dist-info/WHEEL
manga_ocr-0.1.13.dist-info/entry_points.txt
manga_ocr-0.1.13.dist-info/top_level.txt
manga_ocr-0.1.13.dist-info/RECORD
