Metadata-Version: 2.1
Name: manga-ocr
Version: 0.1.13
Summary: OCR for Japanese manga
Author-email: Maciej Budyś <kha-white@mail.com>
License: Apache License
Project-URL: Homepage, https://github.com/kha-white/manga-ocr
Classifier: Programming Language :: Python :: 3
Requires-Python: >=3.6
License-File: LICENSE
Requires-Dist: fire
Requires-Dist: fugashi
Requires-Dist: jaconv
Requires-Dist: loguru
Requires-Dist: numpy <2
Requires-Dist: Pillow >=10.0.0
Requires-Dist: pyperclip
Requires-Dist: torch >=1.0
Requires-Dist: transformers >=4.25.0
Requires-Dist: unidic-lite
Provides-Extra: dev
Requires-Dist: pytest ; extra == 'dev'
Requires-Dist: ruff ; extra == 'dev'
